neighborhood/VERSION
neighborhood/__init__.py
neighborhood/appraise.py
neighborhood/reference.py
neighborhood/search.py
neighborhood/test_appraise.py
neighborhood/test_search.py
neighborhood-0.1.1.dist-info/DESCRIPTION.rst
neighborhood-0.1.1.dist-info/METADATA
neighborhood-0.1.1.dist-info/RECORD
neighborhood-0.1.1.dist-info/WHEEL
neighborhood-0.1.1.dist-info/metadata.json
neighborhood-0.1.1.dist-info/top_level.txt
