Metadata-Version: 2.0
Name: neighborhood
Version: 0.1.1
Summary: Neighborhood Algorithm Optimization and Ensemble Appraisal
Home-page: https://github.com/keithfma/neighborhood
Author: Keith Ma
Author-email: keithfma@gmail.com
License: UNKNOWN
Platform: UNKNOWN
Classifier: Topic :: Scientific/Engineering
Classifier: Programming Language :: Python :: 3 :: Only
Classifier: License :: OSI Approved :: MIT License
Requires-Dist: matplotlib
Requires-Dist: numpy
Requires-Dist: pandas
Requires-Dist: pytest
Requires-Dist: seaborn
